Metadata-Version: 1.1
Name: conservation-scores-dataset
Version: 0.0.1
Summary: Python package providing retrieval for conservation scores.
Home-page: https://github.com/LucaCappelletti94/conservation_scores_dataset
Author: Luca Cappelletti
Author-email: cappelletti.luca94@gmail.com
License: MIT
Platform: UNKNOWN
Classifier: Development Status :: 3 - Alpha
Classifier: License :: OSI Approved :: MIT License
Classifier: Programming Language :: Python :: 3
